stringdiff.py
stringdiff-1.0.3.dist-info/METADATA
stringdiff-1.0.3.dist-info/WHEEL
stringdiff-1.0.3.dist-info/top_level.txt
stringdiff-1.0.3.dist-info/RECORD
