Metadata-Version: 2.1
Name: stringdiff
Version: 1.0.3
Summary: Use edit distance to compare strings
Home-page: https://github.com/yining0713/edit-distance
Author: Lillian Zhu
Author-email: zhuy0713@gmail.com
License: MIT
Platform: UNKNOWN
